pymikro/DejaVuSans.ttf
pymikro/__init__.py
pymikro/maschine_mikro_mk3.json
pymikro-0.15.dist-info/LICENSE
pymikro-0.15.dist-info/METADATA
pymikro-0.15.dist-info/WHEEL
pymikro-0.15.dist-info/top_level.txt
pymikro-0.15.dist-info/RECORD
